tool_create_python_tool/__init__.py
tool_create_python_tool/cli.py
tool_create_python_tool/main.py
tool_create_python_tool/py.typed
tool_create_python_tool-0.1.0.dist-info/METADATA
tool_create_python_tool-0.1.0.dist-info/WHEEL
tool_create_python_tool-0.1.0.dist-info/entry_points.txt
tool_create_python_tool-0.1.0.dist-info/RECORD
